setup.cfg
setup.py
xsms/__init__.py
xsms/__main__.py
xsms/gui.py
xsms/inbox.py
xsms/message_actions_frame.py
xsms/message_frame.py
xsms/outbox.py
xsms/style.py
xsms/textui.py
xsms/ui.py
xsms/utils.py
xsms.egg-info/PKG-INFO
xsms.egg-info/SOURCES.txt
xsms.egg-info/dependency_links.txt
xsms.egg-info/requires.txt
xsms.egg-info/top_level.txt