Metadata-Version: 1.1
Name: xsms
Version: 0.6
Summary: lightweight SMS reader/composer for systems with access to a Sierra em73xx modem (like the Thinkpad X250), with simple xmobar integration
Home-page: https://github.com/smcl/xsms
Author: Sean McLemon
Author-email: sean.mclemon@gmail.com
License: UNKNOWN
Download-URL: https://github.com/smcl/xsms/tarball/0.6
Keywords: thinkpad,em7345,em73xx,sms,xmonad,xmobar
Platform: UNKNOWN
